network_builder/__init__.py
network_builder/__main__.py
network_builder/network_builder.py
network_builder-0.0.3.dist-info/LICENSE
network_builder-0.0.3.dist-info/WHEEL
network_builder-0.0.3.dist-info/METADATA
network_builder-0.0.3.dist-info/RECORD
