Metadata-Version: 2.1
Name: network_builder
Version: 0.0.3
Summary: Infrastructure as code network builder
Author-email: Levy-Y <21.hagymasi.levente.gyula@mechwart.com>
Requires-Python: >=3.10
Requires-Dist: netmiko
Project-URL: Homepage, https://github.com/Levy-Y/Network-Builder/
Project-URL: Repository, https://github.com/Levy-Y/Network-Builder/
